{
  "project_info": {
    "project_number": "51266360786",
    "project_id": "plotvote-ash",
    "storage_bucket": "plotvote-ash.firebasestorage.app"
  },
  "client": [
    {
      "client_info": {
        "mobilesdk_app_id": "1:51266360786:android:df1a90b394a8610599240b",
        "android_client_info": {
          "package_name": "com.example.plotvote"
        }
      },
      "oauth_client": [],
      "api_key": [
        {
          "current_key": "AIzaSyAKX4Ox4scLSoLF-S9tOnh_MoMdpxEAe7Y"
        }
      ],
      "services": {
        "appinvite_service": {
          "other_platform_oauth_client": []
        }
      }
    }
  ],
  "configuration_version": "1"
}